zerobouncesdk/__init__.py
zerobouncesdk/_zb_response.py
zerobouncesdk/zb_confidence.py
zerobouncesdk/zb_delete_file_response.py
zerobouncesdk/zb_exceptions.py
zerobouncesdk/zb_file_status_response.py
zerobouncesdk/zb_get_activity_response.py
zerobouncesdk/zb_get_api_usage_response.py
zerobouncesdk/zb_get_credits_response.py
zerobouncesdk/zb_get_file_response.py
zerobouncesdk/zb_guess_format_response.py
zerobouncesdk/zb_send_file_response.py
zerobouncesdk/zb_validate_batch_element.py
zerobouncesdk/zb_validate_batch_response.py
zerobouncesdk/zb_validate_response.py
zerobouncesdk/zb_validate_status.py
zerobouncesdk/zb_validate_sub_status.py
zerobouncesdk/zerobouncesdk.py
zerobounceindiasdk-1.1.0.dist-info/LICENSE.txt
zerobounceindiasdk-1.1.0.dist-info/METADATA
zerobounceindiasdk-1.1.0.dist-info/WHEEL
zerobounceindiasdk-1.1.0.dist-info/top_level.txt
zerobounceindiasdk-1.1.0.dist-info/RECORD
