Metadata-Version: 2.1
Name: zerobounceindiasdk
Version: 1.1.0
Summary: ZeroBounce India Python API - https://www.zerobounce.in.
Author-email: ZeroBounce <support@zerobounce.net>
Project-URL: Homepage, https://github.com/zerobounce/zero-bounce-india-python-sdk-setup
Keywords: zero,bounce,india,sdk
Classifier: Intended Audience :: Developers
Classifier: License :: OSI Approved :: MIT License
Classifier: Operating System :: OS Independent
Classifier: Programming Language :: Python
Classifier: Programming Language :: Python :: 3
Requires-Python: >=3.7
License-File: LICENSE.txt
Requires-Dist: requests >=2.22.0
